{
  "identity": {
    "persona": "E1: The Anti-AI Designer",
    "mission": "Create a premium, rugged, and dynamic dating app for travelers that breaks the 'generic dating app' mold.",
    "principles": [
      "Fusion over Imitation: Mix 'Tactical Gear' aesthetics with 'Luxury Travel' vibes.",
      "Emotion First: Every interaction should feel 'exciting' and 'urgent'.",
      "Content is King: User photos are the heroes; UI recedes into the dark.",
      "Zoom In: High-impact, full-screen imagery for profiles.",
      "Negative Space: Use deep dark space to create mystery and focus."
    ],
    "anti_patterns": [
      "No generic 'Inter' font for headings.",
      "No flat, boring gray backgrounds. Use texture and depth.",
      "No 'Bootstrap' grids. Use asymmetric, dynamic layouts.",
      "No 'Rainbow' gradients. Stick to the strict Gold/Midnight/Signal palette."
    ]
  },
  "design_system": {
    "theme": "dark",
    "palette": {
      "name": "Midnight Highway",
      "colors": {
        "background": {
          "primary": "#0B1120",
          "secondary": "#111827",
          "tertiary": "#1F2937",
          "glass": "rgba(11, 17, 32, 0.85)"
        },
        "text": {
          "primary": "#F8FAFC",
          "secondary": "#94A3B8",
          "muted": "#64748B"
        },
        "brand": {
          "gold": "#EAB308",
          "gold_dim": "#CA8A04",
          "gold_glow": "rgba(234, 179, 8, 0.5)"
        },
        "functional": {
          "signal_blue": "#3B82F6",
          "success": "#10B981",
          "error": "#EF4444",
          "hot": "#F97316"
        }
      },
      "gradients": {
        "gold_rush": "linear-gradient(135deg, #EAB308 0%, #CA8A04 100%)",
        "midnight_fade": "linear-gradient(to bottom, rgba(11, 17, 32, 0) 0%, #0B1120 100%)",
        "hot_streak": "linear-gradient(135deg, #FF6B35 0%, #EF4444 100%)"
      }
    },
    "typography": {
      "headings": {
        "family": "Barlow Condensed, sans-serif",
        "weights": ["700", "900"],
        "usage": "Uppercase, tight tracking (-0.02em), used for all screen titles and major CTAs."
      },
      "body": {
        "family": "Manrope, sans-serif",
        "weights": ["400", "500", "600"],
        "usage": "Clean, legible, used for bios, chats, and settings."
      }
    },
    "spacing": {
      "scale": "Tailwind default but doubled for 'breathing room' (e.g., p-8 instead of p-4).",
      "grid_gap": "gap-6 or gap-8"
    },
    "radius": {
      "default": "rounded-xl",
      "buttons": "rounded-full",
      "cards": "rounded-2xl"
    },
    "shadows": {
      "glow": "0 0 20px rgba(234, 179, 8, 0.3)",
      "deep": "0 20px 40px rgba(0, 0, 0, 0.6)"
    }
  },
  "components": {
    "buttons": {
      "primary": "bg-gradient-to-r from-brand-gold to-yellow-600 text-background font-bold uppercase tracking-wider hover:scale-105 transition-transform shadow-glow",
      "secondary": "bg-white/10 backdrop-blur-md border border-white/10 text-white hover:bg-white/20",
      "fab": "fixed bottom-24 right-6 w-14 h-14 rounded-full bg-brand-gold text-background shadow-glow flex items-center justify-center z-50 animate-bounce-slow"
    },
    "cards": {
      "profile": "relative w-full aspect-[3/4] rounded-3xl overflow-hidden shadow-deep border border-white/5",
      "glass": "bg-background-glass backdrop-blur-xl border border-white/10 rounded-xl p-6"
    },
    "navigation": {
      "bottom_bar": "fixed bottom-0 left-0 right-0 h-20 bg-background-glass backdrop-blur-2xl border-t border-white/5 flex justify-around items-center z-50",
      "active_tab": "text-brand-gold scale-110 transition-all",
      "inactive_tab": "text-gray-500 hover:text-gray-300"
    },
    "inputs": {
      "default": "bg-white/5 border border-white/10 rounded-lg px-4 py-3 text-white focus:border-brand-gold focus:ring-1 focus:ring-brand-gold transition-all placeholder:text-gray-600"
    }
  },
  "features": {
    "nearby": {
      "prominence": "HIGH",
      "implementation": [
        "Banner on Discover Page: 'Hot Travelers Nearby' (Horizontal Scroll)",
        "Central Tab in Bottom Nav: 'Map' icon",
        "Map View: Dark mode map tiles (CartoDB Dark Matter), Gold pulses for users",
        "FAB: 'Check In' button on Map screen to broadcast location"
      ]
    },
    "chat": {
      "style": "Bubble-free or modern bubbles. Sent: Gold gradient. Received: Dark Glass.",
      "features": ["Typing indicators", "Read receipts", "Reaction picker"]
    },
    "profile": {
      "gallery": "Full-screen vertical scroll or Tappable story-style gallery.",
      "badges": "Neon-style outlines for 'Trucker', 'Pilot', 'Vacationer'."
    }
  },
  "assets": {
    "images": {
      "hero_bg": "https://images.unsplash.com/photo-1549918060-c0c5aa3ded02?crop=entropy&cs=srgb&fm=jpg&q=85",
      "profiles": [
        "https://images.unsplash.com/photo-1677365492809-36819c3cd0f6?crop=entropy&cs=srgb&fm=jpg&q=85",
        "https://images.unsplash.com/photo-1597466372553-872e25a63b11?crop=entropy&cs=srgb&fm=jpg&q=85",
        "https://images.unsplash.com/photo-1662971640032-ed60396966a0?crop=entropy&cs=srgb&fm=jpg&q=85",
        "https://images.unsplash.com/photo-1570369336897-57984b6cf5dc?crop=entropy&cs=srgb&fm=jpg&q=85"
      ],
      "map_marker": "https://images.unsplash.com/photo-1618345190897-73f2b762e4bb?crop=entropy&cs=srgb&fm=jpg&q=85"
    },
    "icons": "Lucide React (default) or Heroicons"
  },
  "universal_guidelines": [
    "Dark colors look good when used independently without gradients. DO NOT use dark colors as gradients.",
    "Don't make generic centered layouts, simplistic gradients, and uniform styling.",
    "Create depth through layered design elements with z-index hierarchy.",
    "Use glass-morphism effects with backdrop filters (12-24px blur).",
    "You MUST NOT apply universal transition. Eg: transition: all. This results in breaking transforms.",
    "You MUST NOT center align the app container.",
    "Always use modern button styles like pill-shaped, or sharp button with interaction animations.",
    "NEVER use AI assistant Emoji characters like 🤖🧠 etc.",
    "Every interaction needs micro-animations.",
    "Use 2-3x more spacing than feels comfortable.",
    "All interactive elements MUST include data-testid attribute."
  ],
  "instructions_to_main_agent": "Follow the 'Midnight Highway' theme strictly. Implement the 'Nearby' feature with maximum prominence as requested. Use the provided image URLs for placeholders. Ensure the app feels 'native' with smooth transitions between screens."
}